buildingclassifier2/__init__.py
buildingclassifier2/btl_utility.py
buildingclassifier2-0.0.8.dist-info/METADATA
buildingclassifier2-0.0.8.dist-info/WHEEL
buildingclassifier2-0.0.8.dist-info/top_level.txt
buildingclassifier2-0.0.8.dist-info/RECORD
