Metadata-Version: 2.1
Name: buildingclassifier2
Version: 0.0.8
Summary: Rule-based building classifier package
Home-page: UNKNOWN
Author: Emeric Szaboky
Author-email: <emeric.szaboky@rakuten.com>
License: UNKNOWN
Keywords: python,first package
Platform: UNKNOWN
Classifier: Development Status :: 3 - Alpha
Classifier: Intended Audience :: Education
Classifier: Programming Language :: Python :: 2
Classifier: Programming Language :: Python :: 3
Classifier: Operating System :: MacOS :: MacOS X
Classifier: Operating System :: Microsoft :: Windows
Requires-Dist: jaconv
Requires-Dist: datetime
Requires-Dist: dask
Requires-Dist: dsdtools
